README
setup.py
abnum/__init__.py
abnum/letter_value.py
abnum/main.py
abnum/math.py
abnum/search.py
abnum.egg-info/PKG-INFO
abnum.egg-info/SOURCES.txt
abnum.egg-info/dependency_links.txt
abnum.egg-info/requires.txt
abnum.egg-info/top_level.txt