Metadata-Version: 1.1
Name: abnum
Version: 0.1.6
Summary: Abnum - Alphabetic numerals package including various letter value substituting systems from ancient times to modern artificial ones
Home-page: https://github.com/markomanninen/abnum
Author: Marko Manninen
Author-email: elonmedia@gmail.com
License: UNKNOWN
Download-URL: https://github.com/markomanninen/abnum/archive/v0.1.6.tar.gz
Keywords: python,jupyter notebook,ancient greek,isopsephy,text analysis
Platform: any
Classifier: Development Status :: 3 - Alpha
Classifier: Intended Audience :: Developers
Classifier: License :: OSI Approved :: MIT License
Classifier: Operating System :: OS Independent
Classifier: Programming Language :: Python
Classifier: Topic :: Software Development :: Libraries
